webmention.py
webmention-0.1.1.dist-info/METADATA
webmention-0.1.1.dist-info/entry_points.txt
webmention-0.1.1.dist-info/WHEEL
webmention-0.1.1.dist-info/RECORD
